Metadata-Version: 2.1
Name: giorgiuertashvilibolo
Version: 0.0.1
Summary: calculator
Home-page: 
Author: Giorgi Uertashvili
Author-email: giouerta97@gmail.com
License: MIT
Keywords: calculator
Classifier: Development Status :: 5 - Production/Stable
Classifier: Intended Audience :: Education
Classifier: Operating System :: Microsoft :: Windows :: Windows 10
Classifier: License :: OSI Approved :: MIT License
Classifier: Programming Language :: Python :: 3
License-File: LICENSE.txt
